raspi_poe_mon/__init__.py
raspi_poe_mon/__main__.py
raspi_poe_mon/ctrl.py
raspi_poe_mon/main.py
raspi_poe_mon/mock.py
raspi_poe_mon/monitor.py
raspi_poe_mon/poe_hat.py
raspi_poe_mon/res/cg-pixel-4x5-mono.otf
raspi_poe_mon/res/cg-pixel-4x5.otf
raspi_poe_mon/res/pcsenior-8px.ttf
raspi_poe_mon/util.py
raspi_poe_mon/version.py
raspi_poe_mon-1.0.0.dist-info/LICENSE
raspi_poe_mon-1.0.0.dist-info/METADATA
raspi_poe_mon-1.0.0.dist-info/WHEEL
raspi_poe_mon-1.0.0.dist-info/entry_points.txt
raspi_poe_mon-1.0.0.dist-info/RECORD
