Metadata-Version: 2.1
Name: raspi-poe-mon
Version: 1.0.0
Summary: A controller for the display and fan of the Raspberry Pi Power Over Ethernet HAT (Type B), compatible with Raspberry Pi 3B+/4B
Home-page: https://github.com/klamann/raspi-poe-mon
License: MIT
Keywords: raspberry-pi,oled-display,monitoring,waveshare,power-over-ethernet
Author: Sebastian Straub
Author-email: sstraub@posteo.de
Requires-Python: >=3.9,<4.0
Classifier: Development Status :: 4 - Beta
Classifier: License :: OSI Approved :: MIT License
Classifier: Programming Language :: Python :: 3
Classifier: Programming Language :: Python :: 3.9
Classifier: Programming Language :: Python :: 3.10
Classifier: Programming Language :: Python :: 3.11
Classifier: Programming Language :: Python :: 3.12
Requires-Dist: luma-oled (>=3.12,<4.0)
Requires-Dist: pillow (>=10.4,<11.0)
Requires-Dist: psutil (>=6.0.0,<7.0.0)
Requires-Dist: typer[all] (>=0.12.3,<0.13.0)
Project-URL: Repository, https://github.com/klamann/raspi-poe-mon
